tunnel_2_by_jumphost/__init__.py
tunnel_2_by_jumphost/tunnel-2-by-jumphost.py
tunnel_2_by_jumphost-0.1.0.dist-info/METADATA
tunnel_2_by_jumphost-0.1.0.dist-info/WHEEL
tunnel_2_by_jumphost-0.1.0.dist-info/entry_points.txt
tunnel_2_by_jumphost-0.1.0.dist-info/RECORD
